connectorx.libs/libcom_err-448cbf49.so.2
connectorx.libs/libcrypto-bdaed0ea.so.1.1
connectorx.libs/libgssapi_krb5-323bbd21.so.2
connectorx.libs/libk5crypto-9a74ff38.so.3
connectorx.libs/libkeyutils-2777d33d.so.1
connectorx.libs/libkrb5-a55300e8.so.3
connectorx.libs/libkrb5support-e6594cfc.so.0
connectorx.libs/libpcre2-8-516f4c9d.so.0
connectorx.libs/libselinux-d0805dcb.so.1
connectorx/Cargo.toml
connectorx/README.md
connectorx/__init__.py
connectorx/connectorx.cpython-310-x86_64-linux-gnu.so
connectorx/connectorx.pyi
connectorx/examples/batch_test.rs
connectorx/examples/jvm_test.rs
connectorx/py.typed
connectorx/src/arrow_batch_iter.rs
connectorx/src/constants.rs
connectorx/src/data_order.rs
connectorx/src/destinations/arrow/arrow_assoc.rs
connectorx/src/destinations/arrow/errors.rs
connectorx/src/destinations/arrow/funcs.rs
connectorx/src/destinations/arrow/mod.rs
connectorx/src/destinations/arrow/typesystem.rs
connectorx/src/destinations/arrowstream/arrow_assoc.rs
connectorx/src/destinations/arrowstream/errors.rs
connectorx/src/destinations/arrowstream/funcs.rs
connectorx/src/destinations/arrowstream/mod.rs
connectorx/src/destinations/arrowstream/typesystem.rs
connectorx/src/destinations/mod.rs
connectorx/src/dispatcher.rs
connectorx/src/errors.rs
connectorx/src/fed_dispatcher.rs
connectorx/src/fed_rewriter.rs
connectorx/src/get_arrow.rs
connectorx/src/lib.rs
connectorx/src/macros.rs
connectorx/src/partition.rs
connectorx/src/source_router.rs
connectorx/src/sources/bigquery/errors.rs
connectorx/src/sources/bigquery/mod.rs
connectorx/src/sources/bigquery/typesystem.rs
connectorx/src/sources/csv/errors.rs
connectorx/src/sources/csv/mod.rs
connectorx/src/sources/csv/typesystem.rs
connectorx/src/sources/dummy/mod.rs
connectorx/src/sources/dummy/typesystem.rs
connectorx/src/sources/mod.rs
connectorx/src/sources/mssql/errors.rs
connectorx/src/sources/mssql/mod.rs
connectorx/src/sources/mssql/typesystem.rs
connectorx/src/sources/mysql/errors.rs
thealtoclef_connectorx-202507.9.0rc0.dist-info/METADATA
thealtoclef_connectorx-202507.9.0rc0.dist-info/WHEEL
thealtoclef_connectorx-202507.9.0rc0.dist-info/licenses/LICENSE
thealtoclef_connectorx-202507.9.0rc0.dist-info/RECORD
