Metadata-Version: 2.4
Name: thealtoclef-connectorx
Version: 202507.9.0rc0
Classifier: Development Status :: 4 - Beta
Classifier: Topic :: Software Development :: Build Tools
Classifier: Environment :: Console
Classifier: Operating System :: OS Independent
Classifier: Intended Audience :: Science/Research
Classifier: Intended Audience :: Developers
Classifier: Intended Audience :: Financial and Insurance Industry
Classifier: Intended Audience :: Healthcare Industry
Classifier: Topic :: Scientific/Engineering
Classifier: Framework :: IPython
Requires-Dist: numpy>=2.1
Requires-Dist: dask[dataframe]>=2021,<2022 ; extra == 'all'
Requires-Dist: pandas>=2 ; extra == 'all'
Requires-Dist: modin>=0.10 ; extra == 'all'
Requires-Dist: polars>=1 ; extra == 'all'
Requires-Dist: pyarrow>=4 ; extra == 'all'
Requires-Dist: dask[dataframe]>=2021,<2022 ; extra == 'dask'
Requires-Dist: pandas>=2 ; extra == 'dask'
Requires-Dist: modin>=0.10 ; extra == 'modin'
Requires-Dist: pandas>=2 ; extra == 'modin'
Requires-Dist: pandas>=2 ; extra == 'pandas'
Requires-Dist: pyarrow>=4 ; extra == 'polars'
Requires-Dist: polars>=1 ; extra == 'polars'
Requires-Dist: pyarrow>=4 ; extra == 'pyarrow'
Provides-Extra: all
Provides-Extra: dask
Provides-Extra: modin
Provides-Extra: pandas
Provides-Extra: polars
Provides-Extra: pyarrow
License-File: LICENSE
Summary: Load data from databases to dataframes, the fastest way.
Keywords: read_sql
Author: Weiyuan Wu <youngw@sfu.ca>
Author-email: SFU Database System Lab <dsl.cs.sfu@gmail.com>
Maintainer-email: Weiyuan Wu <youngw@sfu.ca>
License: MIT
Requires-Python: >=3.10
Project-URL: Homepage, https://github.com/sfu-db/connector-x
Project-URL: Repository, https://github.com/sfu-db/connector-x
Project-URL: Issues, https://github.com/sfu-db/connector-x/issues
Project-URL: Documentation, https://sfu-db.github.io/connector-x/intro.html
